scattr/__init__.py
scattr/scattr.py
scattr-0.0.1.dist-info/METADATA
scattr-0.0.1.dist-info/RECORD
scattr-0.0.1.dist-info/WHEEL
scattr-0.0.1.dist-info/top_level.txt
