Metadata-Version: 2.1
Name: scattr
Version: 0.0.1
Summary: Add user-defined methods to Python classes.
Home-page: https://github.com/marskar/scattr
Author: Martin Skarzynski
Author-email: marskar@gmail.com
License: UNKNOWN
Platform: UNKNOWN
Classifier: Programming Language :: Python :: 3
Classifier: License :: OSI Approved :: MIT License
Classifier: Operating System :: OS Independent
